{
  "courses": [
    {
      "id": "012200",
      "name": "MIND VOLUNTEER",
      "sections": [
        {
          "id": "001",
          "teacher": [
            "Rapee Sangsakorn"
          ],
          "credit_lec": 3,
          "credit_lab": 0,
          "day": "TuF",
          "time": [
            "12.30-15.30"
          ],
          "room": [
            "AKB4801"
          ],
          "seat": 35,
          "enrolled": 32
        },
        {
          "id": "002",
          "teacher": [
            "Rapee Sangsakorn",
            "Staff"
          ],
          "credit_lec": 3,
          "credit_lab": 0,
          "day": "TuF",
          "time": [
            "15.30-18.30"
          ],
          "room": [
            "AKB4801"
          ],
          "seat": 35,
          "enrolled": 35
        }
      ]
    }
  ],
  "add": [
    {
      "body": "{ course: 012200, section: 001 }",
      "id": 1
    }
  ]
}